{"16940697494407s": {"submission": "4407", "time": 1694069749, "score": 0.0, "extra": ["0", "0", "0", "0", "0"]}, "16940684384343s": {"submission": "4343", "time": 1694068438, "score": 50.0, "extra": ["0", "38", "0", "12", "0"]}, "16940703734431s": {"submission": "4431", "time": 1694070373, "score": 0.0, "extra": ["0", "0", "0", "0", "0", "0", "0"]}, "16940671124302s": {"submission": "4302", "time": 1694067112, "score": 100.0, "extra": ["0", "11", "16", "15", "18", "19", "21"]}, "16940688934362s": {"submission": "4362", "time": 1694068893, "score": 50.0, "extra": ["0", "38", "0", "12", "0"]}, "16940637564185s": {"submission": "4185", "time": 1694063756, "score": 61.0, "extra": ["0", "13", "14", "34", "0"]}, "16940705334438s": {"submission": "4438", "time": 1694070533, "score": 0.0, "extra": ["0", "0", "0", "0", "0"]}, "16940680734329s": {"submission": "4329", "time": 1694068073, "score": 0.0, "extra": ["0", "0", "0", "0", "0"]}, "16940690784371s": {"submission": "4371", "time": 1694069078, "score": 4.0, "extra": ["0", "4", "0", "0", "0"]}, "16940699684413s": {"submission": "4413", "time": 1694069968, "score": 0.0, "extra": ["0", "0", "0", "0", "0"]}, "16940707514441s": {"submission": "4441", "time": 1694070751, "score": 0.0, "extra": ["0", "0", "0", "0", "0"]}, "16940654944242s": {"submission": "4242", "time": 1694065494, "score": 0.0, "extra": ["0", "0", "0", "0", "0"]}, "16940716224474s": {"submission": "4474", "time": 1694071622, "score": 0.0, "extra": ["0", "0", "0", "0", "0"]}, "16940650084225s": {"submission": "4225", "time": 1694065008, "score": 45.0, "extra": ["0", "29", "0", "16", "0"]}, "16940694434392s": {"submission": "4392", "time": 1694069443, "score": 0.0, "extra": ["0", "0", "0", "0", "0"]}, "16940703434429s": {"submission": "4429", "time": 1694070343, "score": 0.0, "extra": ["0", "0", "0", "0", "0"]}, "16940714954466s": {"submission": "4466", "time": 1694071495, "score": 0.0, "extra": ["0", "0", "0", "0", "0", "0", "0"]}, "16940649204220s": {"submission": "4220", "time": 1694064920, "score": 60.0, "extra": ["0", "38", "22", "0", "0"]}, "16940708814445s": {"submission": "4445", "time": 1694070881, "score": 0.0, "extra": ["0", "0", "0", "0", "0", "0", "0"]}, "16940668774292s": {"submission": "4292", "time": 1694066877, "score": 0.0, "extra": ["0", "0", "0", "0", "0"]}, "16940690714370s": {"submission": "4370", "time": 1694069071, "score": 0.0, "extra": ["0", "0", "0", "0", "0"]}, "16940697764409s": {"submission": "4409", "time": 1694069776, "score": 61.0, "extra": ["0", "13", "14", "34", "0"]}, "16940692384380s": {"submission": "4380", "time": 1694069238, "score": 44.0, "extra": ["0", "0", "44", "0", "0"]}, "16940686084347s": {"submission": "4347", "time": 1694068608, "score": 0.0, "extra": ["0", "0", "0", "0", "0"]}, "16940637684187s": {"submission": "4187", "time": 1694063768, "score": 0.0, "extra": ["0", "0", "0", "0", "0"]}, "16940618224141s": {"submission": "4141", "time": 1694061822, "score": 0.0, "extra": ["0", "0", "0", "0", "0"]}, "16940668704291s": {"submission": "4291", "time": 1694066870, "score": 45.0, "extra": ["0", "29", "0", "16", "0"]}, "16940639774193s": {"submission": "4193", "time": 1694063977, "score": 0.0, "extra": ["0", "0", "0", "0", "0"]}, "16940645394210s": {"submission": "4210", "time": 1694064539, "score": 0.0, "extra": ["0", "0", "0", "0", "0"]}, "16940651804232s": {"submission": "4232", "time": 1694065180, "score": 0.0, "extra": ["0", "0", "0", "0", "0"]}, "16940627504156s": {"submission": "4156", "time": 1694062750, "score": 4.0, "extra": ["0", "4", "0", "0", "0"]}, "16940638704190s": {"submission": "4190", "time": 1694063870, "score": 0.0, "extra": ["0", "0", "0", "0", "0"]}, "16940659264255s": {"submission": "4255", "time": 1694065926, "score": 61.0, "extra": ["0", "13", "14", "34", "0"]}, "16940619704143s": {"submission": "4143", "time": 1694061970, "score": 100.0, "extra": ["0", "13", "14", "34", "39"]}, "16940633224176s": {"submission": "4176", "time": 1694063322, "score": 0.0, "extra": ["0", "0", "0", "0", "0"]}, "16940708574443s": {"submission": "4443", "time": 1694070857, "score": 0.0, "extra": ["0", "0", "0", "0", "0"]}, "16940714804465s": {"submission": "4465", "time": 1694071480, "score": 0.0, "extra": ["0", "0", "0", "0", "0"]}, "16940626684153s": {"submission": "4153", "time": 1694062668, "score": 61.0, "extra": ["0", "13", "14", "34", "0"]}, "16940671104301s": {"submission": "4301", "time": 1694067110, "score": 38.0, "extra": ["0", "38", "0", "0", "0"]}, "16940690144368s": {"submission": "4368", "time": 1694069014, "score": 0.0, "extra": ["0", "0", "0", "0", "0"]}, "16940651564231s": {"submission": "4231", "time": 1694065156, "score": 50.0, "extra": ["0", "38", "0", "12", "0"]}, "16940700574416s": {"submission": "4416", "time": 1694070057, "score": 100.0, "extra": ["0", "13", "14", "34", "39"]}, "16940641334196s": {"submission": "4196", "time": 1694064133, "score": 0.0, "extra": ["0", "0", "0", "0", "0"]}, "16940717984485s": {"submission": "4485", "time": 1694071798, "score": 14.0, "extra": ["0", "0", "14", "0", "0"]}, "16940717314483s": {"submission": "4483", "time": 1694071731, "score": 45.0, "extra": ["0", "29", "0", "16", "0"]}, "16940648034217s": {"submission": "4217", "time": 1694064803, "score": 61.0, "extra": ["0", "13", "14", "34", "0"]}, "16940655864245s": {"submission": "4245", "time": 1694065586, "score": 100.0, "extra": ["0", "29", "44", "16", "11"]}, "16940711814457s": {"submission": "4457", "time": 1694071181, "score": 4.2, "extra": ["0", "2", "2.2", "0", "0"]}, "16940651404229s": {"submission": "4229", "time": 1694065140, "score": 45.0, "extra": ["0", "29", "0", "16", "0"]}, "16940644324204s": {"submission": "4204", "time": 1694064432, "score": 0.0, "extra": ["0", "0", "0", "0", "0"]}, "16940638994192s": {"submission": "4192", "time": 1694063899, "score": 0.0, "extra": ["0", "0", "0", "0", "0"]}, "16940650644226s": {"submission": "4226", "time": 1694065064, "score": 0.0, "extra": ["0", "0", "0", "0", "0"]}, "16940659344256s": {"submission": "4256", "time": 1694065934, "score": 0.0, "extra": ["0", "0", "0", "0", "0"]}, "16940679664326s": {"submission": "4326", "time": 1694067966, "score": 0.0, "extra": ["0", "0", "0", "0", "0"]}, "16940630174160s": {"submission": "4160", "time": 1694063017, "score": 61.0, "extra": ["0", "13", "14", "34", "0"]}, "16940673154310s": {"submission": "4310", "time": 1694067315, "score": 0.0, "extra": ["0", "0", "0", "0", "0"]}, "16940653154237s": {"submission": "4237", "time": 1694065315, "score": 0.0, "extra": ["0", "0", "0", "0", "0"]}, "16940696714403s": {"submission": "4403", "time": 1694069671, "score": 0.0, "extra": ["0", "0", "0", "0", "0"]}, "16940632624173s": {"submission": "4173", "time": 1694063262, "score": 0.0, "extra": ["0", "0", "0", "0", "0"]}, "16940665664277s": {"submission": "4277", "time": 1694066566, "score": 0.0, "extra": ["0", "0", "0", "0", "0"]}, "16940691884375s": {"submission": "4375", "time": 1694069188, "score": 0.0, "extra": ["0", "0", "0", "0", "0"]}, "16940715594471s": {"submission": "4471", "time": 1694071559, "score": 0.0, "extra": ["0", "0", "0", "0", "0"]}, "16940674154313s": {"submission": "4313", "time": 1694067415, "score": 0.0, "extra": ["0", "0", "0", "0", "0"]}, "16940695514396s": {"submission": "4396", "time": 1694069551, "score": 0.0, "extra": ["0", "0", "0", "0", "0"]}, "16940659984259s": {"submission": "4259", "time": 1694065998, "score": 0.0, "extra": ["0", "0", "0", "0", "0"]}, "16940688764360s": {"submission": "4360", "time": 1694068876, "score": 47.0, "extra": ["0", "13", "0", "34", "0"]}, "16940704084433s": {"submission": "4433", "time": 1694070408, "score": 0.0, "extra": ["0", "0", "0", "0", "0"]}, "16940712294460s": {"submission": "4460", "time": 1694071229, "score": 0.0, "extra": ["0", "0", "0", "0", "0"]}, "16940716294475s": {"submission": "4475", "time": 1694071629, "score": 4.0, "extra": ["0", "4", "0", "0", "0"]}, "16940687334352s": {"submission": "4352", "time": 1694068733, "score": 47.0, "extra": ["0", "13", "0", "34", "0"]}, "16940704734435s": {"submission": "4435", "time": 1694070473, "score": 0.0, "extra": ["0", "0", "0", "0", "0"]}, "16940647644214s": {"submission": "4214", "time": 1694064764, "score": 0.0, "extra": ["0", "0", "0", "0", "0"]}, "16940631944169s": {"submission": "4169", "time": 1694063194, "score": 13.0, "extra": ["0", "13", "0", "0", "0"]}, "16940647104213s": {"submission": "4213", "time": 1694064710, "score": 100.0, "extra": ["0", "29", "44", "16", "11"]}, "16940697694408s": {"submission": "4408", "time": 1694069769, "score": 0.0, "extra": ["0", "0", "0", "0", "0"]}, "16940624534150s": {"submission": "4150", "time": 1694062453, "score": 61.0, "extra": ["0", "13", "14", "34", "0"]}, "16940702904426s": {"submission": "4426", "time": 1694070290, "score": 38.0, "extra": ["0", "38", "0", "0", "0"]}, "16940670524299s": {"submission": "4299", "time": 1694067052, "score": 0.0, "extra": ["0", "0", "0", "0", "0", "0", "0"]}, "16940676224319s": {"submission": "4319", "time": 1694067622, "score": 0.0, "extra": ["0", "0", "0", "0", "0"]}, "16940711224454s": {"submission": "4454", "time": 1694071122, "score": 0.0, "extra": ["0", "0", "0", "0", "0"]}, "16940654254240s": {"submission": "4240", "time": 1694065425, "score": 0.0, "extra": ["0", "0", "0", "0", "0"]}, "16940636124182s": {"submission": "4182", "time": 1694063612, "score": 0.0, "extra": ["0", "0", "0", "0", "0"]}, "16940705154437s": {"submission": "4437", "time": 1694070515, "score": 38.0, "extra": ["0", "38", "0", "0", "0"]}, "16940662904267s": {"submission": "4267", "time": 1694066290, "score": 0.0, "extra": ["0", "0", "0", "0", "0"]}, "16940715904473s": {"submission": "4473", "time": 1694071590, "score": 45.0, "extra": ["0", "29", "0", "16", "0"]}, "16940632784174s": {"submission": "4174", "time": 1694063278, "score": 0.0, "extra": ["0", "0", "0", "0", "0"]}, "16940669774296s": {"submission": "4296", "time": 1694066977, "score": 4.0, "extra": ["0", "4", "0", "0", "0"]}, "16940651514230s": {"submission": "4230", "time": 1694065151, "score": 0.0, "extra": ["0", "0", "0", "0", "0"]}, "16940688694359s": {"submission": "4359", "time": 1694068869, "score": 100.0, "extra": ["0", "11", "16", "15", "18", "19", "21"]}, "16940673954311s": {"submission": "4311", "time": 1694067395, "score": 0.0, "extra": ["0", "0", "0", "0", "0"]}, "16940634524178s": {"submission": "4178", "time": 1694063452, "score": 13.0, "extra": ["0", "13", "0", "0", "0"]}, "16940712284459s": {"submission": "4459", "time": 1694071228, "score": 0.0, "extra": ["0", "0", "0", "0", "0"]}, "16940630444162s": {"submission": "4162", "time": 1694063044, "score": 100.0, "extra": ["0", "13", "14", "34", "39"]}, "16940642194198s": {"submission": "4198", "time": 1694064219, "score": 0.0, "extra": ["0", "0", "0", "0", "0"]}, "16940651964233s": {"submission": "4233", "time": 1694065196, "score": 0.0, "extra": ["0", "0", "0", "0", "0"]}, "16940710324449s": {"submission": "4449", "time": 1694071032, "score": 0.0, "extra": ["0", "0", "0", "0", "0"]}, "16940692134379s": {"submission": "4379", "time": 1694069213, "score": 0.0, "extra": ["0", "0", "0", "0", "0"]}, "16940659794258s": {"submission": "4258", "time": 1694065979, "score": 0.0, "extra": ["0", "0", "0", "0", "0"]}, "16940652214234s": {"submission": "4234", "time": 1694065221, "score": 45.0, "extra": ["0", "29", "0", "16", "0"]}, "16940681944335s": {"submission": "4335", "time": 1694068194, "score": 0.0, "extra": ["0", "0", "0", "0", "0", "0", "0"]}, "16940695604397s": {"submission": "4397", "time": 1694069560, "score": 0.0, "extra": ["0", "0", "0", "0", "0"]}, "16940675484316s": {"submission": "4316", "time": 1694067548, "score": 44.0, "extra": ["0", "0", "44", "0", "0"]}, "16940623324147s": {"submission": "4147", "time": 1694062332, "score": 100.0, "extra": ["0", "13", "14", "34", "39"]}, "16940667604286s": {"submission": "4286", "time": 1694066760, "score": 100.0, "extra": ["0", "38", "22", "12", "28"]}, "16940673974312s": {"submission": "4312", "time": 1694067397, "score": 0.0, "extra": ["0", "0", "0", "0", "0"]}, "16940701564419s": {"submission": "4419", "time": 1694070156, "score": 29.0, "extra": ["0", "29", "0", "0", "0"]}, "16940668394289s": {"submission": "4289", "time": 1694066839, "score": 4.0, "extra": ["0", "4", "0", "0", "0"]}, "16940636664183s": {"submission": "4183", "time": 1694063666, "score": 0.0, "extra": ["0", "0", "0", "0", "0"]}, "16940711514455s": {"submission": "4455", "time": 1694071151, "score": 0.0, "extra": ["0", "0", "0", "0", "0", "0", "0"]}, "16940671244303s": {"submission": "4303", "time": 1694067124, "score": 50.0, "extra": ["0", "38", "0", "12", "0"]}, "16940685274344s": {"submission": "4344", "time": 1694068527, "score": 0.0, "extra": ["0", "0", "0", "0", "0"]}, "16940658634254s": {"submission": "4254", "time": 1694065863, "score": 61.0, "extra": ["0", "13", "14", "34", "0"]}, "16940630514163s": {"submission": "4163", "time": 1694063051, "score": 45.0, "extra": ["0", "29", "0", "16", "0"]}, "16940709174446s": {"submission": "4446", "time": 1694070917, "score": 0.0, "extra": ["0", "0", "0", "0", "0"]}, "16940665974280s": {"submission": "4280", "time": 1694066597, "score": 44.0, "extra": ["0", "0", "44", "0", "0"]}, "16940662544266s": {"submission": "4266", "time": 1694066254, "score": 100.0, "extra": ["0", "38", "22", "12", "28"]}, "16940631574167s": {"submission": "4167", "time": 1694063157, "score": 61.0, "extra": ["0", "13", "14", "34", "0"]}, "16940693784387s": {"submission": "4387", "time": 1694069378, "score": 0.0, "extra": ["0", "0", "0", "0", "0"]}, "16940715104467s": {"submission": "4467", "time": 1694071510, "score": 50.0, "extra": ["0", "38", "0", "12", "0"]}, "16940708554442s": {"submission": "4442", "time": 1694070855, "score": 32.0, "extra": ["0", "4", "11", "17", "0"]}, "16940717044480s": {"submission": "4480", "time": 1694071704, "score": 0.0, "extra": ["0", "0", "0", "0", "0", "0", "0"]}, "16940665384275s": {"submission": "4275", "time": 1694066538, "score": 0.0, "extra": ["0", "0", "0", "0", "0"]}, "16940702254422s": {"submission": "4422", "time": 1694070225, "score": 0.0, "extra": ["0", "0", "0", "0", "0"]}, "16940702764425s": {"submission": "4425", "time": 1694070276, "score": 38.0, "extra": ["0", "38", "0", "0", "0"]}, "16940674554314s": {"submission": "4314", "time": 1694067455, "score": 50.0, "extra": ["0", "38", "0", "12", "0"]}, "16940642994200s": {"submission": "4200", "time": 1694064299, "score": 100.0, "extra": ["0", "38", "22", "12", "28"]}, "16940682924339s": {"submission": "4339", "time": 1694068292, "score": 50.0, "extra": ["0", "38", "0", "12", "0"]}, "16940627134155s": {"submission": "4155", "time": 1694062713, "score": 0.0, "extra": ["0", "0", "0", "0", "0"]}, "16940701674420s": {"submission": "4420", "time": 1694070167, "score": 0.0, "extra": ["0", "0", "0", "0", "0"]}, "16940656204246s": {"submission": "4246", "time": 1694065620, "score": 45.0, "extra": ["0", "29", "0", "16", "0"]}, "16940700594417s": {"submission": "4417", "time": 1694070059, "score": 0.0, "extra": ["0", "0", "0", "0", "0"]}, "16940701234418s": {"submission": "4418", "time": 1694070123, "score": 0.0, "extra": ["0", "0", "0", "0", "0"]}, "16940687274351s": {"submission": "4351", "time": 1694068727, "score": 61.0, "extra": ["0", "13", "14", "34", "0"]}, "16940628004157s": {"submission": "4157", "time": 1694062800, "score": 100.0, "extra": ["0", "13", "14", "34", "39"]}, "16940679304323s": {"submission": "4323", "time": 1694067930, "score": 13.0, "extra": ["0", "13", "0", "0", "0"]}, "16940699954415s": {"submission": "4415", "time": 1694069995, "score": 0.0, "extra": ["0", "0", "0", "0", "0"]}, "16940706534440s": {"submission": "4440", "time": 1694070653, "score": 38.0, "extra": ["0", "38", "0", "0", "0"]}, "16940644764205s": {"submission": "4205", "time": 1694064476, "score": 0.0, "extra": ["0", "0", "0", "0", "0"]}, "16940683724342s": {"submission": "4342", "time": 1694068372, "score": 0.0, "extra": ["0", "0", "0", "0", "0", "0", "0"]}, "16940626784154s": {"submission": "4154", "time": 1694062678, "score": 100.0, "extra": ["0", "29", "44", "16", "11"]}, "16940704704434s": {"submission": "4434", "time": 1694070470, "score": 49.0, "extra": ["0", "4", "11", "17", "17"]}, "16940688564358s": {"submission": "4358", "time": 1694068856, "score": 0.0, "extra": ["0", "0", "0", "0", "0"]}, "16940689664365s": {"submission": "4365", "time": 1694068966, "score": 27.0, "extra": ["0", "11", "16", "0", "0", "0", "0"]}, "16940644994207s": {"submission": "4207", "time": 1694064499, "score": 0.0, "extra": ["0", "0", "0", "0", "0"]}, "16940686714349s": {"submission": "4349", "time": 1694068671, "score": 0.0, "extra": ["0", "0", "0", "0", "0"]}, "16940663824271s": {"submission": "4271", "time": 1694066382, "score": 0.0, "extra": ["0", "0", "0", "0", "0"]}, "16940690984372s": {"submission": "4372", "time": 1694069098, "score": 49.0, "extra": ["0", "4", "11", "17", "17"]}, "16940622314145s": {"submission": "4145", "time": 1694062231, "score": 0.0, "extra": ["0", "0", "0", "0", "0"]}, "16940646844212s": {"submission": "4212", "time": 1694064684, "score": 50.0, "extra": ["0", "38", "0", "12", "0"]}, "16940671714307s": {"submission": "4307", "time": 1694067171, "score": 38.0, "extra": ["0", "38", "0", "0", "0"]}, "16940625364151s": {"submission": "4151", "time": 1694062536, "score": 61.0, "extra": ["0", "13", "14", "34", "0"]}, "16940697024405s": {"submission": "4405", "time": 1694069702, "score": 0.0, "extra": ["0", "0", "0", "0", "0"]}, "16940658194253s": {"submission": "4253", "time": 1694065819, "score": 0.0, "extra": ["0", "0", "0", "0", "0"]}, "16940715584470s": {"submission": "4470", "time": 1694071558, "score": 0.0, "extra": ["0", "0", "0", "0", "0"]}, "16940637674186s": {"submission": "4186", "time": 1694063767, "score": 0.0, "extra": ["0", "0", "0", "0", "0"]}, "16940692674382s": {"submission": "4382", "time": 1694069267, "score": 50.0, "extra": ["0", "38", "0", "12", "0"]}, "16940715764472s": {"submission": "4472", "time": 1694071576, "score": 50.0, "extra": ["0", "38", "0", "12", "0"]}, "16940717134481s": {"submission": "4481", "time": 1694071713, "score": 14.0, "extra": ["0", "0", "14", "0", "0"]}, "16940626094152s": {"submission": "4152", "time": 1694062609, "score": 100.0, "extra": ["0", "13", "14", "34", "39"]}, "16940635484181s": {"submission": "4181", "time": 1694063548, "score": 0.0, "extra": ["0", "0", "0", "0", "0"]}, "16940694104390s": {"submission": "4390", "time": 1694069410, "score": 61.0, "extra": ["0", "13", "14", "34", "0"]}, "16940645354209s": {"submission": "4209", "time": 1694064535, "score": 100.0, "extra": ["0", "29", "44", "16", "11"]}, "16940704004432s": {"submission": "4432", "time": 1694070400, "score": 0.0, "extra": ["0", "0", "0", "0", "0"]}, "16940693384386s": {"submission": "4386", "time": 1694069338, "score": 4.0, "extra": ["0", "4", "0", "0", "0"]}, "16940680444328s": {"submission": "4328", "time": 1694068044, "score": 29.0, "extra": ["0", "29", "0", "0", "0"]}, "16940685754345s": {"submission": "4345", "time": 1694068575, "score": 0.0, "extra": ["0", "0", "0", "0", "0"]}, "16940717804484s": {"submission": "4484", "time": 1694071780, "score": 0.0, "extra": ["0", "0", "0", "0", "0", "0", "0"]}, "16940631194165s": {"submission": "4165", "time": 1694063119, "score": 0.0, "extra": ["0", "0", "0", "0", "0"]}, "16940632364172s": {"submission": "4172", "time": 1694063236, "score": 0.0, "extra": ["0", "0", "0", "0", "0"]}, "16940692754383s": {"submission": "4383", "time": 1694069275, "score": 4.0, "extra": ["0", "4", "0", "0", "0"]}, "16940691454374s": {"submission": "4374", "time": 1694069145, "score": 0.0, "extra": ["0", "0", "0", "0", "0"]}, "16940701754421s": {"submission": "4421", "time": 1694070175, "score": 0.0, "extra": ["0", "0", "0", "0", "0"]}, "16940713464464s": {"submission": "4464", "time": 1694071346, "score": 38.0, "extra": ["0", "38", "0", "0", "0"]}, "16940661934264s": {"submission": "4264", "time": 1694066193, "score": 0.0, "extra": ["0", "0", "0", "0", "0"]}, "16940634784180s": {"submission": "4180", "time": 1694063478, "score": 61.0, "extra": ["0", "13", "14", "34", "0"]}, "16940715134468s": {"submission": "4468", "time": 1694071513, "score": 6.2, "extra": ["0", "4", "2.2", "0", "0"]}, "16940686204348s": {"submission": "4348", "time": 1694068620, "score": 50.0, "extra": ["0", "38", "0", "12", "0"]}, "16940702594424s": {"submission": "4424", "time": 1694070259, "score": 0.0, "extra": ["0", "0", "0", "0", "0"]}, "16940672794309s": {"submission": "4309", "time": 1694067279, "score": 0.0, "extra": ["0", "0", "0", "0", "0"]}, "16940693824388s": {"submission": "4388", "time": 1694069382, "score": 0.0, "extra": ["0", "0", "0", "0", "0"]}, "16940674714315s": {"submission": "4315", "time": 1694067471, "score": 100.0, "extra": ["0", "38", "22", "12", "28"]}, "16940716394477s": {"submission": "4477", "time": 1694071639, "score": 0.0, "extra": ["0", "0", "0", "0", "0"]}, "16940675934317s": {"submission": "4317", "time": 1694067593, "score": 100.0, "extra": ["0", "38", "22", "12", "28"]}, "16940648214218s": {"submission": "4218", "time": 1694064821, "score": 0.0, "extra": ["0", "0", "0", "0", "0"]}, "16940682824337s": {"submission": "4337", "time": 1694068282, "score": 0.0, "extra": ["0", "0", "0", "0", "0"]}, "16940665804279s": {"submission": "4279", "time": 1694066580, "score": 0.0, "extra": ["0", "0", "0", "0", "0"]}, "16940665114273s": {"submission": "4273", "time": 1694066511, "score": 0.0, "extra": ["0", "0", "0", "0", "0"]}, "16940678284322s": {"submission": "4322", "time": 1694067828, "score": 0.0, "extra": ["0", "0", "0", "0", "0"]}, "16940655534243s": {"submission": "4243", "time": 1694065553, "score": 0.0, "extra": ["0", "0", "0", "0", "0"]}, "16940710834451s": {"submission": "4451", "time": 1694071083, "score": 0.0, "extra": ["0", "0", "0", "0", "0"]}, "16940628934158s": {"submission": "4158", "time": 1694062893, "score": 14.0, "extra": ["0", "0", "14", "0", "0"]}, "16940668544290s": {"submission": "4290", "time": 1694066854, "score": 0.0, "extra": ["0", "0", "0", "0", "0"]}, "16940665434276s": {"submission": "4276", "time": 1694066543, "score": 4.0, "extra": ["0", "4", "0", "0", "0"]}, "16940711214453s": {"submission": "4453", "time": 1694071121, "score": 48.0, "extra": ["0", "0", "14", "34", "0"]}, "16940689554363s": {"submission": "4363", "time": 1694068955, "score": 47.0, "extra": ["0", "13", "0", "34", "0"]}, "16940679494325s": {"submission": "4325", "time": 1694067949, "score": 0.0, "extra": ["0", "0", "0", "0", "0"]}, "16940670944300s": {"submission": "4300", "time": 1694067094, "score": 0.0, "extra": ["0", "0", "0", "0", "0"]}, "16940666704282s": {"submission": "4282", "time": 1694066670, "score": 44.0, "extra": ["0", "0", "44", "0", "0"]}, "16940692094378s": {"submission": "4378", "time": 1694069209, "score": 45.0, "extra": ["0", "29", "0", "16", "0"]}, "16940669614295s": {"submission": "4295", "time": 1694066961, "score": 0.0, "extra": ["0", "0", "0", "0", "0"]}, "16940716324476s": {"submission": "4476", "time": 1694071632, "score": 4.4, "extra": ["0", "0", "4.4", "0", "0"]}, "16940615734137s": {"submission": "4137", "time": 1694061573, "score": 100.0, "extra": ["0", "29", "44", "16", "11"]}, "16940653734239s": {"submission": "4239", "time": 1694065373, "score": 50.0, "extra": ["0", "38", "0", "12", "0"]}, "16940703264427s": {"submission": "4427", "time": 1694070326, "score": 100.0, "extra": ["0", "29", "44", "16", "11"]}, "16940683724341s": {"submission": "4341", "time": 1694068372, "score": 50.0, "extra": ["0", "38", "0", "12", "0"]}, "16940642964199s": {"submission": "4199", "time": 1694064296, "score": 100.0, "extra": ["0", "29", "44", "16", "11"]}, "16940689824366s": {"submission": "4366", "time": 1694068982, "score": 0.0, "extra": ["0", "0", "0", "0", "0"]}, "16940630634164s": {"submission": "4164", "time": 1694063063, "score": 14.0, "extra": ["0", "0", "14", "0", "0"]}, "16940629644159s": {"submission": "4159", "time": 1694062964, "score": 0.0, "extra": ["0", "0", "0", "0", "0"]}, "16940647754215s": {"submission": "4215", "time": 1694064775, "score": 0.0, "extra": ["0", "0", "0", "0", "0"]}, "16940699534412s": {"submission": "4412", "time": 1694069953, "score": 0.0, "extra": ["0", "0", "0", "0", "0"]}, "16940671494304s": {"submission": "4304", "time": 1694067149, "score": 89.0, "extra": ["0", "29", "44", "16", "0"]}, "16940681184332s": {"submission": "4332", "time": 1694068118, "score": 50.0, "extra": ["0", "38", "0", "12", "0"]}, "16940632224171s": {"submission": "4171", "time": 1694063222, "score": 0.0, "extra": ["0", "0", "0", "0", "0"]}, "16940670104297s": {"submission": "4297", "time": 1694067010, "score": 0.0, "extra": ["0", "0", "0", "0", "0"]}, "16940677134320s": {"submission": "4320", "time": 1694067713, "score": 0.0, "extra": ["0", "0", "0", "0", "0"]}, "16940692544381s": {"submission": "4381", "time": 1694069254, "score": 0.0, "extra": ["0", "0", "0", "0", "0"]}, "16940687904356s": {"submission": "4356", "time": 1694068790, "score": 100.0, "extra": ["0", "38", "22", "12", "28"]}, "16940712854462s": {"submission": "4462", "time": 1694071285, "score": 45.0, "extra": ["0", "29", "0", "16", "0"]}, "16940697334406s": {"submission": "4406", "time": 1694069733, "score": 0.0, "extra": ["0", "0", "0", "0", "0", "0", "0"]}, "16940694724393s": {"submission": "4393", "time": 1694069472, "score": 0.0, "extra": ["0", "0", "0", "0", "0"]}, "16940671634306s": {"submission": "4306", "time": 1694067163, "score": 0.0, "extra": ["0", "0", "0", "0", "0"]}, "16940708574444s": {"submission": "4444", "time": 1694070857, "score": 61.0, "extra": ["0", "13", "14", "34", "0"]}, "16940693164385s": {"submission": "4385", "time": 1694069316, "score": 0.0, "extra": ["0", "0", "0", "0", "0"]}, "16940663124268s": {"submission": "4268", "time": 1694066312, "score": 0.0, "extra": ["0", "0", "0", "0", "0"]}, "16940696604402s": {"submission": "4402", "time": 1694069660, "score": 6.2, "extra": ["0", "4", "2.2", "0", "0"]}, "16940689654364s": {"submission": "4364", "time": 1694068965, "score": 50.0, "extra": ["0", "38", "0", "12", "0"]}, "16940616364139s": {"submission": "4139", "time": 1694061636, "score": 0.0, "extra": ["0", "0", "0", "0", "0"]}, "16940652834236s": {"submission": "4236", "time": 1694065283, "score": 45.0, "extra": ["0", "29", "0", "16", "0"]}, "16940696494401s": {"submission": "4401", "time": 1694069649, "score": 0.0, "extra": ["0", "0", "0", "0", "0"]}, "16940643854202s": {"submission": "4202", "time": 1694064385, "score": 0.0, "extra": ["0", "0", "0", "0", "0"]}, "16940656434247s": {"submission": "4247", "time": 1694065643, "score": 0.0, "extra": ["0", "0", "0", "0", "0"]}, "16940653464238s": {"submission": "4238", "time": 1694065346, "score": 100.0, "extra": ["0", "38", "22", "12", "28"]}, "16940688784361s": {"submission": "4361", "time": 1694068878, "score": 0.0, "extra": ["0", "0", "0", "0", "0"]}, "16940654864241s": {"submission": "4241", "time": 1694065486, "score": 0.0, "extra": ["0", "0", "0", "0", "0"]}, "16940687774354s": {"submission": "4354", "time": 1694068777, "score": 0.0, "extra": ["0", "0", "0", "0", "0"]}, "16940696474400s": {"submission": "4400", "time": 1694069647, "score": 0.0, "extra": ["0", "0", "0", "0", "0", "0", "0"]}, "16940704924436s": {"submission": "4436", "time": 1694070492, "score": 38.0, "extra": ["0", "38", "0", "0", "0"]}, "16940667624287s": {"submission": "4287", "time": 1694066762, "score": 0.0, "extra": ["0", "0", "0", "0", "0"]}, "16940665744278s": {"submission": "4278", "time": 1694066574, "score": 0.0, "extra": ["0", "0", "0", "0", "0"]}, "16940695064394s": {"submission": "4394", "time": 1694069506, "score": 0.0, "extra": ["0", "0", "0", "0", "0"]}, "16940638884191s": {"submission": "4191", "time": 1694063888, "score": 13.0, "extra": ["0", "13", "0", "0", "0"]}, "16940666754283s": {"submission": "4283", "time": 1694066675, "score": 0.0, "extra": ["0", "0", "0", "0", "0"]}, "16940632114170s": {"submission": "4170", "time": 1694063211, "score": 100.0, "extra": ["0", "13", "14", "34", "39"]}, "16940634544179s": {"submission": "4179", "time": 1694063454, "score": 0.0, "extra": ["0", "0", "0", "0", "0"]}, "16940687074350s": {"submission": "4350", "time": 1694068707, "score": 0.0, "extra": ["0", "0", "0", "0", "0"]}, "16940665354274s": {"submission": "4274", "time": 1694066535, "score": 0.0, "extra": ["0", "0", "0", "0", "0"]}, "16940667364285s": {"submission": "4285", "time": 1694066736, "score": 49.0, "extra": ["0", "4", "11", "17", "17"]}, "16940679684327s": {"submission": "4327", "time": 1694067968, "score": 61.0, "extra": ["0", "13", "14", "34", "0"]}, "16940687514353s": {"submission": "4353", "time": 1694068751, "score": 0.0, "extra": ["0", "0", "0", "0", "0"]}, "16940656474248s": {"submission": "4248", "time": 1694065647, "score": 0.0, "extra": ["0", "0", "0", "0", "0"]}, "16940660654261s": {"submission": "4261", "time": 1694066065, "score": 0.0, "extra": ["0", "0", "0", "0", "0"]}, "16940640504195s": {"submission": "4195", "time": 1694064050, "score": 60.0, "extra": ["0", "38", "22", "0", "0"]}, "16940682594336s": {"submission": "4336", "time": 1694068259, "score": 0.0, "extra": ["0", "0", "0", "0", "0"]}, "16940681554333s": {"submission": "4333", "time": 1694068155, "score": 61.0, "extra": ["0", "13", "14", "34", "0"]}, "16940679424324s": {"submission": "4324", "time": 1694067942, "score": 0.0, "extra": ["0", "0", "0", "0", "0"]}, "16940692784384s": {"submission": "4384", "time": 1694069278, "score": 0.0, "extra": ["0", "0", "0", "0", "0"]}, "16940671584305s": {"submission": "4305", "time": 1694067158, "score": 0.0, "extra": ["0", "0", "0", "0", "0"]}, "16940693944389s": {"submission": "4389", "time": 1694069394, "score": 13.0, "extra": ["0", "13", "0", "0", "0"]}, "16940657114250s": {"submission": "4250", "time": 1694065711, "score": 0.0, "extra": ["0", "0", "0", "0", "0"]}, "16940641494197s": {"submission": "4197", "time": 1694064149, "score": 0.0, "extra": ["0", "0", "0", "0", "0"]}, "16940687964357s": {"submission": "4357", "time": 1694068796, "score": 0.0, "extra": ["0", "0", "0", "0", "0"]}, "16940633724177s": {"submission": "4177", "time": 1694063372, "score": 14.0, "extra": ["0", "0", "14", "0", "0"]}, "16940650964228s": {"submission": "4228", "time": 1694065096, "score": 45.0, "extra": ["0", "29", "0", "16", "0"]}, "16940647884216s": {"submission": "4216", "time": 1694064788, "score": 0.0, "extra": ["0", "0", "0", "0", "0"]}, "16940703574430s": {"submission": "4430", "time": 1694070357, "score": 0.0, "extra": ["0", "0", "0", "0", "0"]}, "16940712814461s": {"submission": "4461", "time": 1694071281, "score": 38.0, "extra": ["0", "38", "0", "0", "0"]}, "16940633134175s": {"submission": "4175", "time": 1694063313, "score": 0.0, "extra": ["0", "0", "0", "0", "0"]}, "16940622874146s": {"submission": "4146", "time": 1694062287, "score": 100.0, "extra": ["0", "13", "14", "34", "39"]}, "16940685994346s": {"submission": "4346", "time": 1694068599, "score": 0.0, "extra": ["0", "0", "0", "0", "0"]}, "16940624504149s": {"submission": "4149", "time": 1694062450, "score": 100.0, "extra": ["0", "29", "44", "16", "11"]}, "16940683494340s": {"submission": "4340", "time": 1694068349, "score": 0.0, "extra": ["0", "0", "0", "0", "0"]}, "16940717244482s": {"submission": "4482", "time": 1694071724, "score": 50.0, "extra": ["0", "38", "0", "12", "0"]}, "16940687874355s": {"submission": "4355", "time": 1694068787, "score": 0.0, "extra": ["0", "0", "0", "0", "0"]}, "16940631714168s": {"submission": "4168", "time": 1694063171, "score": 0.0, "extra": ["0", "0", "0", "0", "0"]}, "16940712044458s": {"submission": "4458", "time": 1694071204, "score": 18.0, "extra": ["0", "0", "0", "0", "18", "0", "0"]}, "16940695184395s": {"submission": "4395", "time": 1694069518, "score": 14.0, "extra": ["0", "0", "14", "0", "0"]}, "16940713454463s": {"submission": "4463", "time": 1694071345, "score": 0.0, "extra": ["0", "0", "0", "0", "0"]}, "16940650014224s": {"submission": "4224", "time": 1694065001, "score": 45.0, "extra": ["0", "29", "0", "16", "0"]}, "16940689974367s": {"submission": "4367", "time": 1694068997, "score": 100.0, "extra": ["0", "29", "44", "16", "11"]}, "16940617954140s": {"submission": "4140", "time": 1694061795, "score": 100.0, "extra": ["0", "29", "44", "16", "11"]}, "16940662214265s": {"submission": "4265", "time": 1694066221, "score": 0.0, "extra": ["0", "0", "0", "0", "0"]}, "16940645284208s": {"submission": "4208", "time": 1694064528, "score": 0.0, "extra": ["0", "0", "0", "0", "0"]}, "16940670234298s": {"submission": "4298", "time": 1694067023, "score": 0.0, "extra": ["0", "0", "0", "0", "0"]}, "16940643164201s": {"submission": "4201", "time": 1694064316, "score": 100.0, "extra": ["0", "13", "14", "34", "39"]}, "16940650654227s": {"submission": "4227", "time": 1694065065, "score": 0.0, "extra": ["0", "0", "0", "0", "0"]}, "16940682864338s": {"submission": "4338", "time": 1694068286, "score": 0.0, "extra": ["0", "0", "0", "0", "0"]}, "16940659374257s": {"submission": "4257", "time": 1694065937, "score": 100.0, "extra": ["0", "38", "22", "12", "28"]}, "16940698384410s": {"submission": "4410", "time": 1694069838, "score": 0.0, "extra": ["0", "0", "0", "0", "0"]}, "16940681014330s": {"submission": "4330", "time": 1694068101, "score": 0.0, "extra": ["0", "0", "0", "0", "0"]}, "16940671834308s": {"submission": "4308", "time": 1694067183, "score": 0.0, "extra": ["0", "0", "0", "0", "0"]}, "16940702454423s": {"submission": "4423", "time": 1694070245, "score": 29.0, "extra": ["0", "29", "0", "0", "0"]}, "16940690564369s": {"submission": "4369", "time": 1694069056, "score": 50.0, "extra": ["0", "38", "0", "12", "0"]}, "16940638654189s": {"submission": "4189", "time": 1694063865, "score": 0.0, "extra": ["0", "0", "0", "0", "0"]}, "16940694194391s": {"submission": "4391", "time": 1694069419, "score": 31.7562249008, "extra": ["0", "4", "4.4", "6.8", "16.56"]}, "16940648384219s": {"submission": "4219", "time": 1694064838, "score": 4.0, "extra": ["0", "4", "0", "0", "0"]}, "16940696094398s": {"submission": "4398", "time": 1694069609, "score": 49.0, "extra": ["0", "4", "11", "17", "17"]}, "16940664574272s": {"submission": "4272", "time": 1694066457, "score": 0.0, "extra": ["0", "0", "0", "0", "0"]}, "16940699774414s": {"submission": "4414", "time": 1694069977, "score": 0.0, "extra": ["0", "0", "0", "0", "0"]}, "16940667954288s": {"submission": "4288", "time": 1694066795, "score": 45.0, "extra": ["0", "29", "0", "16", "0"]}, "16940658054252s": {"submission": "4252", "time": 1694065805, "score": 0.0, "extra": ["0", "0", "0", "0", "0"]}, "16940715294469s": {"submission": "4469", "time": 1694071529, "score": 0.0, "extra": ["0", "0", "0", "0", "0"]}, "16940631264166s": {"submission": "4166", "time": 1694063126, "score": 100.0, "extra": ["0", "29", "44", "16", "11"]}, "16940677914321s": {"submission": "4321", "time": 1694067791, "score": 0.0, "extra": ["0", "0", "0", "0", "0"]}, "16940652754235s": {"submission": "4235", "time": 1694065275, "score": 100.0, "extra": ["0", "29", "44", "16", "11"]}, "16940657484251s": {"submission": "4251", "time": 1694065748, "score": 44.0, "extra": ["0", "0", "44", "0", "0"]}, "16940615964138s": {"submission": "4138", "time": 1694061596, "score": 100.0, "extra": ["0", "13", "14", "34", "39"]}, "16940666774284s": {"submission": "4284", "time": 1694066677, "score": 0.0, "extra": ["0", "0", "0", "0", "0"]}, "16940710844452s": {"submission": "4452", "time": 1694071084, "score": 50.0, "extra": ["0", "38", "0", "12", "0"]}, "16940681034331s": {"submission": "4331", "time": 1694068103, "score": 0.0, "extra": ["0", "0", "0", "0", "0"]}, "16940666424281s": {"submission": "4281", "time": 1694066642, "score": 100.0, "extra": ["0", "29", "44", "16", "11"]}, "16940709624447s": {"submission": "4447", "time": 1694070962, "score": 0.0, "extra": ["0", "0", "0", "0", "0", "0", "0"]}, "16940663514269s": {"submission": "4269", "time": 1694066351, "score": 0.0, "extra": ["0", "0", "0", "0", "0"]}, "16940644944206s": {"submission": "4206", "time": 1694064494, "score": 0.0, "extra": ["0", "0", "0", "0", "0"]}, "16940661254262s": {"submission": "4262", "time": 1694066125, "score": 0.0, "extra": ["0", "0", "0", "0", "0"]}, "16940660244260s": {"submission": "4260", "time": 1694066024, "score": 100.0, "extra": ["0", "38", "22", "12", "28"]}, "16940621324144s": {"submission": "4144", "time": 1694062132, "score": 0.0, "extra": ["0", "0", "0", "0", "0"]}, "16940716884479s": {"submission": "4479", "time": 1694071688, "score": 0.0, "extra": ["0", "0", "0", "0", "0"]}, "16940676164318s": {"submission": "4318", "time": 1694067616, "score": 0.0, "extra": ["0", "0", "0", "0", "0"]}, "16940681564334s": {"submission": "4334", "time": 1694068156, "score": 29.0, "extra": ["0", "29", "0", "0", "0"]}, "16940656664249s": {"submission": "4249", "time": 1694065666, "score": 0.0, "extra": ["0", "0", "0", "0", "0"]}, "16940691984377s": {"submission": "4377", "time": 1694069198, "score": 0.0, "extra": ["0", "0", "0", "0", "0"]}, "16940624444148s": {"submission": "4148", "time": 1694062444, "score": 100.0, "extra": ["0", "38", "22", "12", "28"]}, "16940716654478s": {"submission": "4478", "time": 1694071665, "score": 0.0, "extra": ["0", "0", "0", "0", "0"]}, "16940645504211s": {"submission": "4211", "time": 1694064550, "score": 45.0, "extra": ["0", "29", "0", "16", "0"]}, "16940636914184s": {"submission": "4184", "time": 1694063691, "score": 0.0, "extra": ["0", "0", "0", "0", "0"]}, "16940640224194s": {"submission": "4194", "time": 1694064022, "score": 0.0, "extra": ["0", "0", "0", "0", "0"]}, "16940699274411s": {"submission": "4411", "time": 1694069927, "score": 0.0, "extra": ["0", "0", "0", "0", "0"]}, "16940669404294s": {"submission": "4294", "time": 1694066940, "score": 0.0, "extra": ["0", "0", "0", "0", "0"]}, "16940691894376s": {"submission": "4376", "time": 1694069189, "score": 50.0, "extra": ["0", "38", "0", "12", "0"]}, "16940669314293s": {"submission": "4293", "time": 1694066931, "score": 45.0, "extra": ["0", "29", "0", "16", "0"]}, "16940705434439s": {"submission": "4439", "time": 1694070543, "score": 0.0, "extra": ["0", "0", "0", "0", "0"]}, "16940649314221s": {"submission": "4221", "time": 1694064931, "score": 45.0, "extra": ["0", "29", "0", "16", "0"]}, "16940630344161s": {"submission": "4161", "time": 1694063034, "score": 0.0, "extra": ["0", "0", "0", "0", "0"]}, "16940649554223s": {"submission": "4223", "time": 1694064955, "score": 4.0, "extra": ["0", "4", "0", "0", "0"]}, "16940691044373s": {"submission": "4373", "time": 1694069104, "score": 0.0, "extra": ["0", "0", "0", "0", "0"]}, "16940703354428s": {"submission": "4428", "time": 1694070335, "score": 0.0, "extra": ["0", "0", "0", "0", "0"]}, "16940649434222s": {"submission": "4222", "time": 1694064943, "score": 61.0, "extra": ["0", "13", "14", "34", "0"]}, "16940644184203s": {"submission": "4203", "time": 1694064418, "score": 29.0, "extra": ["0", "29", "0", "0", "0"]}, "16940637904188s": {"submission": "4188", "time": 1694063790, "score": 0.0, "extra": ["0", "0", "0", "0", "0"]}, "16940619424142s": {"submission": "4142", "time": 1694061942, "score": 0.0, "extra": ["0", "0", "0", "0", "0"]}, "16940711574456s": {"submission": "4456", "time": 1694071157, "score": 0.0, "extra": ["0", "0", "0", "0", "0"]}, "16940696344399s": {"submission": "4399", "time": 1694069634, "score": 0.0, "extra": ["0", "0", "0", "0", "0"]}, "16940655794244s": {"submission": "4244", "time": 1694065579, "score": 0.0, "extra": ["0", "0", "0", "0", "0"]}, "16940661344263s": {"submission": "4263", "time": 1694066134, "score": 50.0, "extra": ["0", "38", "0", "12", "0"]}, "16940710594450s": {"submission": "4450", "time": 1694071059, "score": 100.0, "extra": ["0", "4", "11", "17", "68"]}, "16940696934404s": {"submission": "4404", "time": 1694069693, "score": 0.0, "extra": ["0", "0", "0", "0", "0"]}, "16940709684448s": {"submission": "4448", "time": 1694070968, "score": 0.0, "extra": ["0", "0", "0", "0", "0"]}, "16940663634270s": {"submission": "4270", "time": 1694066363, "score": 0.0, "extra": ["0", "0", "0", "0", "0", "0", "0"]}}